remote_read_sql/__init__.py
remote_read_sql/get_db_connection.py
remote_read_sql/get_ssh_connection.py
remote_read_sql/remote_connect.py
remote_read_sql/remote_read_sql.py
remote_read_sql/safe_sql.py
remote_read_sql-1.3.0.dist-info/licenses/LICENSE
remote_read_sql-1.3.0.dist-info/WHEEL
remote_read_sql-1.3.0.dist-info/METADATA
remote_read_sql-1.3.0.dist-info/RECORD
