Metadata-Version: 2.4
Name: remote-read-sql
Version: 1.3.0
Summary: Securely read sql into a pandas dataframe from a remote mysql DB
Keywords: pandas,ssh,mysql,remote,dataframe
Author: Erik van Widenfelt
Author-email: Erik van Widenfelt <ew2789@gmail.com>
License-Expression: MIT
License-File: LICENSE
Classifier: Development Status :: 5 - Production/Stable
Classifier: Operating System :: OS Independent
Classifier: Programming Language :: Python :: 3.11
Classifier: Programming Language :: Python :: 3.12
Classifier: Programming Language :: Python :: 3.13
Requires-Dist: mysqlclient>=2.2.7
Requires-Dist: pandas>=2.3.3
Requires-Dist: paramiko==2.9.3
Requires-Dist: python-dotenv>=1.1.1
Requires-Dist: sqlalchemy>=2.0.44
Requires-Dist: sqlglot>=27.28.1
Requires-Dist: sshtunnel>=0.4.0
Requires-Python: >=3.11, <3.14
